hlpy_business_rule_engine/__init__.py
hlpy_business_rule_engine/rule.py
hlpy_business_rule_engine/rule_engine.py
hlpy_business_rule_engine-0.1.0.dist-info/LICENSE
hlpy_business_rule_engine-0.1.0.dist-info/METADATA
hlpy_business_rule_engine-0.1.0.dist-info/WHEEL
hlpy_business_rule_engine-0.1.0.dist-info/top_level.txt
hlpy_business_rule_engine-0.1.0.dist-info/RECORD
